{
  "VahidOOnLine": 242928,
  "mwarmonitor": 9917,
  "pm_afshaa": 91900,
  "iaghapour": 2642,
  "DEJradio": 5155,
  "mamlekate": 103604,
  "VahidOnline": 75804,
  "kianmeli1": 87685,
  "IranIntlTV": 339756,
  "FoxNewsChannel": 3,
  "Shin_Persian": 6320,
  "Iliaen": 4437,
  "CnnBrk": 247615,
  "reutersworldchannel": 151524,
  "ManotoTV": 105878,
  "FarsiVOA": 219089,
  "DW_Farsi": 125321,
  "Persian_Trend_Official": 15344,
  "RadioFarda": 157723,
  "IranianMinds": 21074,
  "BBCPersian": 282435,
  "IranWire": 65,
  "idfinfarsi": 11659,
  "Dirty_Kids": 390571,
  "Hranews": 113247,
  "officialrezapahlavi": 1835,
  "configx2ray": 38663,
  "manototv": 105878,
  "alonews": 123751,
  "farsi_fox_news": 89200,
  "FoxNewsTwitter": 342426,
  "CNNfarsiCHANNEL": 51273,
  "WithYashar": 12942
}