{
  "VahidOOnLine": 243079,
  "mwarmonitor": 9949,
  "pm_afshaa": 91959,
  "iaghapour": 2646,
  "DEJradio": 5190,
  "mamlekate": 103604,
  "VahidOnline": 75822,
  "kianmeli1": 87685,
  "IranIntlTV": 339915,
  "FoxNewsChannel": 3,
  "Shin_Persian": 6331,
  "Iliaen": 4437,
  "CnnBrk": 247615,
  "reutersworldchannel": 151526,
  "ManotoTV": 105878,
  "FarsiVOA": 219191,
  "DW_Farsi": 125352,
  "Persian_Trend_Official": 15412,
  "RadioFarda": 157749,
  "IranianMinds": 21155,
  "BBCPersian": 282509,
  "IranWire": 65,
  "idfinfarsi": 11687,
  "Dirty_Kids": 390670,
  "Hranews": 113286,
  "officialrezapahlavi": 1835,
  "configx2ray": 38663,
  "manototv": 105878,
  "alonews": 124008,
  "farsi_fox_news": 89200,
  "FoxNewsTwitter": 342454,
  "CNNfarsiCHANNEL": 51273,
  "WithYashar": 13078
}