{
  "VahidOOnLine": 241390,
  "mwarmonitor": 9439,
  "pm_afshaa": 91173,
  "iaghapour": 2624,
  "DEJradio": 4829,
  "mamlekate": 103564,
  "VahidOnline": 75600,
  "kianmeli1": 87546,
  "IranIntlTV": 338284,
  "FoxNewsChannel": 3,
  "Shin_Persian": 6126,
  "Iliaen": 4434,
  "CnnBrk": 247615,
  "reutersworldchannel": 151524,
  "ManotoTV": 105728,
  "FarsiVOA": 218320,
  "DW_Farsi": 124984,
  "Persian_Trend_Official": 14632,
  "RadioFarda": 157435,
  "IranianMinds": 20509,
  "BBCPersian": 281722,
  "IranWire": 65,
  "idfinfarsi": 11617,
  "Dirty_Kids": 389905,
  "Hranews": 113085,
  "officialrezapahlavi": 1834,
  "configx2ray": 38663,
  "manototv": 105728,
  "alonews": 121648,
  "farsi_fox_news": 89200,
  "FoxNewsTwitter": 342076,
  "CNNfarsiCHANNEL": 51273,
  "WithYashar": 11871
}